Workbook

Sheet 1.报价汇总
B1: 体彩衍生品商城小程序 — 系统报价表
B2: 聚焦维度：C 端小程序 + 运营管理后台 ｜ 计价单位：人民币（元） ｜ 增值税：13%
B4: 项目名称 | C4: 体彩衍生品商城小程序（UniApp C 端 + Vue3 运营管理后台） | J4: 角色单价（蓝字可调）
B5: 交付周期 | C5: 约 18 周（按里程碑推进） | J5: 角色 | K5: 元/天
B6: 报价日期 | C6: 2026-06-25 | J6: 小程序开发工程师 | K6: 1300
B7: 计价方式 | C7: 人天计费（角色单价 × 实际工作量）；工作量按二级模块逐项核算 | J7: 前端开发工程师 | K7: 1300
J8: 后端开发工程师 | K8: 1500
B9: 维度 / 模块 | C9: 二级项数 | D9: 人天 | E9: 金额(元) | G9: 占比 | H9: 说明 | J9: UI 设计师 | K9: 1000
B10: 一、C 端小程序（UniApp + Vue 3） | C10: 17 | D10: =SUM('2.C端小程序'!E6:E22) | E10: =SUM('2.C端小程序'!G6:G22) | G10: =E10/$E$13 | H10: 含 13 个核心页面 + UI 视觉升级 + 联调 | J10: 测试工程师 | K10: 900
B11: 二、运营管理后台（Vue 3 + Element Plus） | C11: 18 | D11: =SUM('3.运营管理后台'!E6:E23) | E11: =SUM('3.运营管理后台'!G6:G23) | G11: =E11/$E$13 | H11: 含 11 个核心页面 + 系统配置双端同步 + 联调 | J11: 运维工程师 | K11: 1200
B12: 三、配套支撑（联调/测试/管理/部署） | C12: 4 | D12: =SUM('4.配套支撑'!F6:F9) | E12: =SUM('4.配套支撑'!H6:H9) | G12: =E12/$E$13 | H12: 为双端交付所必需的最少支撑项 | J12: 项目经理 | K12: 1500
B13: 开发费用合计 | C13: =C10+C11+C12 | D13: =D10+D11+D12 | E13: =E10+E11+E12 | G13: 100.0% | H13: 税前 | J13: 架构师 | K13: 2500
B14: 增值税（13%） | E14: =E13*0.13 | H14: 可按客户性质调整（如小规模纳税人 3%）
B15: 🟢 项目总价（含税） | E15: =E13+E14 | H15: 人民币
B17: 维度占比速览
B18: 维度 | C18: 占比 | E18: 可视化（■ ≈ 2%）
B19: C 端小程序 | C19: =E10/$E$13 | E19: =REPT("■",ROUND(E10/$E$13*50,0))
B20: 运营管理后台 | C20: =E11/$E$13 | E20: =REPT("■",ROUND(E11/$E$13*50,0))
B21: 配套支撑 | C21: =E12/$E$13 | E21: =REPT("■",ROUND(E12/$E$13*50,0))
B23: 说明：本表聚焦 C 端小程序与运营管理后台两个维度；后端服务（Spring Boot 13 模块）已开发完成，本报价仅按需投入联调工时，不重复计费；如需新增/调整后端模块，可按后端开发工程师 ¥1500/人天增算。

Sheet 2.C端小程序
B1: 一、C 端小程序 — 功能模块清单（UniApp + Vue 3 + Pinia）
B2: 工作量按二级模块核算；蓝色单元格可调，金额 = 人天 × 角色单价（VLOOKUP）
J4: 角色单价（蓝字可调）
B5: 序号 | C5: 二级模块 | D5: 角色 | E5: 人天 | F5: 单价(元/天) | G5: 金额(元) | H5: 功能说明 | J5: 角色 | K5: 元/天
B6: 1.1 | C6: 基础架构搭建 | D6: 小程序开发工程师 | E6: 5 | F6: =VLOOKUP(D6,$J$6:$K$13,2,FALSE) | G6: =E6*F6 | H6: UniApp + Vue 3 + Pinia 项目初始化、目录结构、路由、请求封装、Token 持久化、环境变量 | J6: 小程序开发工程师 | K6: 1300
B7: 1.2 | C7: 公共组件库 | D7: 小程序开发工程师 | E7: 3 | F7: =VLOOKUP(D7,$J$6:$K$13,2,FALSE) | G7: =E7*F7 | H7: 商品卡片、加载/空状态、Toast、Modal、骨架屏、Tabbar 组件 | J7: 前端开发工程师 | K7: 1300
B8: 1.3 | C8: 首页 | D8: 小程序开发工程师 | E8: 4 | F8: =VLOOKUP(D8,$J$6:$K$13,2,FALSE) | G8: =E8*F8 | H8: 轮播 Banner、分类网格、推荐商品流、活动位、Tabbar 切换 | J8: 后端开发工程师 | K8: 1500
B9: 1.4 | C9: 商品分类页 | D9: 小程序开发工程师 | E9: 2 | F9: =VLOOKUP(D9,$J$6:$K$13,2,FALSE) | G9: =E9*F9 | H9: 左侧分类树、右侧商品列表、关键词搜索 | J9: UI 设计师 | K9: 1000
B10: 1.5 | C10: 商品列表页 | D10: 小程序开发工程师 | E10: 3 | F10: =VLOOKUP(D10,$J$6:$K$13,2,FALSE) | G10: =E10*F10 | H10: 筛选（价格/销量/综合）、排序、列表/网格切换、上拉加载 | J10: 测试工程师 | K10: 900
B11: 1.6 | C11: 商品详情页 | D11: 小程序开发工程师 | E11: 3 | F11: =VLOOKUP(D11,$J$6:$K$13,2,FALSE) | G11: =E11*F11 | H11: 图片轮播、规格 SKU 选择、价格/库存、加购、推荐位 | J11: 运维工程师 | K11: 1200
B12: 1.7 | C12: 购物车页 | D12: 小程序开发工程师 | E12: 3 | F12: =VLOOKUP(D12,$J$6:$K$13,2,FALSE) | G12: =E12*F12 | H12: 勾选、数量增减、删除、合计、置底结算栏固定（54px）、长列表完整滚动 | J12: 项目经理 | K12: 1500
B13: 1.8 | C13: 订单确认页 | D13: 小程序开发工程师 | E13: 3 | F13: =VLOOKUP(D13,$J$6:$K$13,2,FALSE) | G13: =E13*F13 | H13: 地址选择、商品清单、备注、运费计算、提交订单 | J13: 架构师 | K13: 2500
B14: 1.9 | C14: 支付页 | D14: 小程序开发工程师 | E14: 2 | F14: =VLOOKUP(D14,$J$6:$K$13,2,FALSE) | G14: =E14*F14 | H14: 微信支付模态框、支付结果、订单跳转
B15: 1.10 | C15: 订单列表页 | D15: 小程序开发工程师 | E15: 2 | F15: =VLOOKUP(D15,$J$6:$K$13,2,FALSE) | G15: =E15*F15 | H15: 状态 Tab、订单卡片、状态时间线入口
B16: 1.11 | C16: 订单详情页 | D16: 小程序开发工程师 | E16: 2 | F16: =VLOOKUP(D16,$J$6:$K$13,2,FALSE) | G16: =E16*F16 | H16: 状态时间线、物流跟踪、申请退款入口、再次购买
B17: 1.12 | C17: 退款申请页 | D17: 小程序开发工程师 | E17: 2 | F17: =VLOOKUP(D17,$J$6:$K$13,2,FALSE) | G17: =E17*F17 | H17: 退款原因、金额、凭证图片上传、提交审核
B18: 1.13 | C18: 收货地址管理 | D18: 小程序开发工程师 | E18: 2 | F18: =VLOOKUP(D18,$J$6:$K$13,2,FALSE) | G18: =E18*F18 | H18: 地址列表、新增/编辑、默认地址、删除、地区选择器
B19: 1.14 | C19: 个人中心 | D19: 小程序开发工程师 | E19: 2 | F19: =VLOOKUP(D19,$J$6:$K$13,2,FALSE) | G19: =E19*F19 | H19: 用户信息、订单入口、设置、客服、关于
B20: 1.15 | C20: 登录/注册 | D20: 小程序开发工程师 | E20: 2 | F20: =VLOOKUP(D20,$J$6:$K$13,2,FALSE) | G20: =E20*F20 | H20: 手机号验证码、微信一键授权、Token 存储与续签
B21: 1.16 | C21: C 端 UI 视觉升级 | D21: UI 设计师 | E21: 5 | F21: =VLOOKUP(D21,$J$6:$K$13,2,FALSE) | G21: =E21*F21 | H21: 奶油玫瑰粉（#fb7185）主题、薄荷绿撞色、纯奶油底色（#fdfbf7）、字体与圆角规范、皮肤系统
B22: 1.17 | C22: C 端联调与缺陷修复 | D22: 小程序开发工程师 | E22: 5 | F22: =VLOOKUP(D22,$J$6:$K$13,2,FALSE) | G22: =E22*F22 | H22: 与后端接口联调、Bug 修复、兼容性测试（iOS/Android）、性能优化
C23: 小计 | E23: =SUM(E6:E22) | G23: =SUM(G6:G22) | H23: —

Sheet 3.运营管理后台
B1: 二、运营管理后台 — 功能模块清单（Vue 3 + Element Plus）
B2: 工作量按二级模块核算；蓝色单元格可调，金额 = 人天 × 角色单价（VLOOKUP）
J4: 角色单价（蓝字可调）
B5: 序号 | C5: 二级模块 | D5: 角色 | E5: 人天 | F5: 单价(元/天) | G5: 金额(元) | H5: 功能说明 | J5: 角色 | K5: 元/天
B6: 2.1 | C6: 基础架构搭建 | D6: 前端开发工程师 | E6: 4 | F6: =VLOOKUP(D6,$J$6:$K$13,2,FALSE) | G6: =E6*F6 | H6: Vue 3 + Vite + Element Plus + Pinia + Vue Router + Axios 工程初始化、目录结构、权限路由 | J6: 小程序开发工程师 | K6: 1300
B7: 2.2 | C7: 公共组件库 | D7: 前端开发工程师 | E7: 4 | F7: =VLOOKUP(D7,$J$6:$K$13,2,FALSE) | G7: =E7*F7 | H7: 表格（搜索/分页/列控制）、表单、对话框、上传、富文本、图表组件 | J7: 前端开发工程师 | K7: 1300
B8: 2.3 | C8: 登录与权限 | D8: 前端开发工程师 | E8: 2 | F8: =VLOOKUP(D8,$J$6:$K$13,2,FALSE) | G8: =E8*F8 | H8: 账号密码登录、Token、路由守卫、按钮级权限、操作日志 | J8: 后端开发工程师 | K8: 1500
B9: 2.4 | C9: 仪表盘 | D9: 前端开发工程师 | E9: 4 | F9: =VLOOKUP(D9,$J$6:$K$13,2,FALSE) | G9: =E9*F9 | H9: 核心指标卡片、订单/销售趋势图表、TOP 商品、待办任务 | J9: UI 设计师 | K9: 1000
B10: 2.5 | C10: 商品管理-列表 | D10: 前端开发工程师 | E10: 3 | F10: =VLOOKUP(D10,$J$6:$K$13,2,FALSE) | G10: =E10*F10 | H10: 商品列表、上架/下架、批量操作、修改价格/库存、详情预览 | J10: 测试工程师 | K10: 900
B11: 2.6 | C11: 商品管理-分类 | D11: 前端开发工程师 | E11: 2 | F11: =VLOOKUP(D11,$J$6:$K$13,2,FALSE) | G11: =E11*F11 | H11: 分类树形结构、拖拽排序、新增/编辑/删除、关联商品 | J11: 运维工程师 | K11: 1200
B12: 2.7 | C12: 订单管理-列表 | D12: 前端开发工程师 | E12: 3 | F12: =VLOOKUP(D12,$J$6:$K$13,2,FALSE) | G12: =E12*F12 | H12: 订单查询、状态筛选、状态流转、导出、详情查看 | J12: 项目经理 | K12: 1500
B13: 2.8 | C13: 订单管理-退款审核 | D13: 前端开发工程师 | E13: 3 | F13: =VLOOKUP(D13,$J$6:$K$13,2,FALSE) | G13: =E13*F13 | H13: 退款申请列表、详情、凭证查看、同意/拒绝、原因记录 | J13: 架构师 | K13: 2500
B14: 2.9 | C14: 渠道商管理 | D14: 前端开发工程师 | E14: 3 | F14: =VLOOKUP(D14,$J$6:$K$13,2,FALSE) | G14: =E14*F14 | H14: 渠道商列表、详情、入驻审核、佣金率配置、二维码生成
B15: 2.10 | C15: 供货商管理 | D15: 前端开发工程师 | E15: 2 | F15: =VLOOKUP(D15,$J$6:$K$13,2,FALSE) | G15: =E15*F15 | H15: 供货商列表、详情、接单配置、结算账户
B16: 2.11 | C16: 地区运营管理 | D16: 前端开发工程师 | E16: 2 | F16: =VLOOKUP(D16,$J$6:$K$13,2,FALSE) | G16: =E16*F16 | H16: 地区树、运营账号绑定、地区数据看板
B17: 2.12 | C17: 财务管理-账单 | D17: 前端开发工程师 | E17: 3 | F17: =VLOOKUP(D17,$J$6:$K$13,2,FALSE) | G17: =E17*F17 | H17: 资金账单、佣金账单、对账、导出、结算操作
B18: 2.13 | C18: Banner 营销管理 | D18: 前端开发工程师 | E18: 2 | F18: =VLOOKUP(D18,$J$6:$K$13,2,FALSE) | G18: =E18*F18 | H18: Banner 列表、图片上传、排序、生效时间、点击跳转
B19: 2.14 | C19: 系统配置-全局参数 | D19: 前端开发工程师 | E19: 1 | F19: =VLOOKUP(D19,$J$6:$K$13,2,FALSE) | G19: =E19*F19 | H19: 系统开关、阈值、限流等参数化配置
B20: 2.15 | C20: 系统配置-内容装修 | D20: 前端开发工程师 | E20: 3 | F20: =VLOOKUP(D20,$J$6:$K$13,2,FALSE) | G20: =E20*F20 | H20: C 端首页 Banner 所见即所得装修、主副标题、Base64 背景图上传与预览
B21: 2.16 | C21: 系统配置-地区运营账号 | D21: 前端开发工程师 | E21: 1 | F21: =VLOOKUP(D21,$J$6:$K$13,2,FALSE) | G21: =E21*F21 | H21: 地区运营账号管理、权限分配、绑定地区
B22: 2.17 | C22: 后台 UI 高保真设计 | D22: UI 设计师 | E22: 5 | F22: =VLOOKUP(D22,$J$6:$K$13,2,FALSE) | G22: =E22*F22 | H22: 高保真 HTML 模拟器、卡片化 Tab 布局、操作反馈设计、风格统一
B23: 2.18 | C23: 后台联调与缺陷修复 | D23: 前端开发工程师 | E23: 4 | F23: =VLOOKUP(D23,$J$6:$K$13,2,FALSE) | G23: =E23*F23 | H23: 与后端接口联调、Bug 修复、IE/Edge/Chrome 兼容、性能优化
C24: 小计 | E24: =SUM(E6:E23) | G24: =SUM(G6:G23) | H24: —

Sheet 4.配套支撑
B1: 三、配套支撑 — 为双端交付所必需的最少支撑项
B2: 聚焦维度外的支撑性工作，按实际发生工时结算；蓝色单元格可调
J4: 角色单价（蓝字可调）
B5: 序号 | C5: 支撑项 | D5: 工作内容 | E5: 角色 | F5: 人天 | G5: 单价(元/天) | H5: 金额(元) | J5: 角色 | K5: 元/天
B6: 3.1 | C6: 后端接口联调支撑 | D6: 后端 Java Spring Boot 工程师配合小程序/后台联调，处理接口联调问题、字段对齐、版本同步 | E6: 后端开发工程师 | F6: 10 | G6: =VLOOKUP(E6,$J$6:$K$13,2,FALSE) | H6: =F6*G6 | J6: 小程序开发工程师 | K6: 1300
B7: 3.2 | C7: 测试与质量保障 | D7: 功能用例执行、回归、Bug 跟踪与回归验证（双端） | E7: 测试工程师 | F7: 12 | G7: =VLOOKUP(E7,$J$6:$K$13,2,FALSE) | H7: =F7*G7 | J7: 前端开发工程师 | K7: 1300
B8: 3.3 | C8: 项目管理 | D8: 项目计划制定、进度跟踪、需求变更控制、跨端沟通协调、文档管理 | E8: 项目经理 | F8: 8 | G8: =VLOOKUP(E8,$J$6:$K$13,2,FALSE) | H8: =F8*G8 | J8: 后端开发工程师 | K8: 1500
B9: 3.4 | C9: 部署与上线支持 | D9: Docker 镜像构建、CI/CD、首次部署、上线后 7×8 小时值守 | E9: 运维工程师 | F9: 5 | G9: =VLOOKUP(E9,$J$6:$K$13,2,FALSE) | H9: =F9*G9 | J9: UI 设计师 | K9: 1000
C10: 小计 | D10: — | F10: =SUM(F6:F9) | H10: =SUM(H6:H9) | J10: 测试工程师 | K10: 900
J11: 运维工程师 | K11: 1200
J12: 项目经理 | K12: 1500
J13: 架构师 | K13: 2500

Sheet 5.报价说明
B1: 报价说明与假设
B3: 条款 | C3: 内容
B4: 报价范围 | C4: 本次报价聚焦于体彩衍生品商城小程序的 C 端小程序（UniApp + Vue 3）与运营管理后台（Vue 3 + Element Plus）两个核心交付维度。后端服务（Spring Boot 13 模块、32 张数据表）已开发完成，本报价仅按需投入联调工时，不重复计费。
B5: 计价方式 | C5: 人天计费：按二级模块逐项核算工作量（蓝色单元格可调），金额 = 人天 × 角色单价；角色单价右侧比照表可整表调整，所有金额自动重算。
B6: 角色单价依据 | C6: 依据 2026 年中国中端软件外包市场行情：架构师 ¥2500、后端 ¥1500、前端/小程序 ¥1300、UI ¥1000、测试 ¥900、运维 ¥1200、PM ¥1500。
B7: 工作日 | C7: 1 人天 = 1 个工程师 1 天（8 小时）有效产出，不含沟通、会议、低效时间。
B8: 包含内容 | C8: 需求评审、二级模块设计、编码实现、单元自测、Code Review 配合、内部联调、Bug 修复一轮、代码移交、必要的文档编写。
B9: 不包含内容 | C9: 服务器/域名/SSL 等基础设施费用、第三方服务费（短信/支付/对象存储）、微信审核费、超过一轮的需求变更与重构、数据迁移（除非另议）、上线后长期运维（按月另议）。
B10: 里程碑付款 | C10: 建议里程碑：①合同签订 30% ②C 端提测 30% ③后台提测 20% ④验收上线 20%（具体比例可协商）。
B11: 交付物 | C11: 源代码、构建产物、API 联调文档、部署手册、运维交接文档、双端高保真 HTML 模拟器。
B12: 知识产权 | C12: 项目尾款付清后，源代码及文档知识产权归委托方所有；乙方保留通用工具与组件的复用权。
B13: 风险与变更 | C13: 需求变更超过总人天 10% 需签订补充协议；不可抗力（政策合规调整等）双方协商。
B14: 有效期 | C14: 本报价自报价日起 30 天内有效；逾期需重新评估工作量与单价。
B15: 备注 | C15: 工作量按标准复杂度估算；若客户对 UI/交互/性能有定制化高要求，工时需上浮 10%~30%。
